dexmotion.cpython-313-x86_64-linux-gnu.so
dexmotion.pyi
dexmotion.build/.gitignore
dexmotion-0.3.1.dist-info/METADATA
dexmotion-0.3.1.dist-info/WHEEL
dexmotion-0.3.1.dist-info/top_level.txt
dexmotion-0.3.1.dist-info/RECORD
