Metadata-Version: 2.4
Name: dexmotion
Version: 0.3.1
Author-email: Dexmate <contact@dexmate.ai>
Classifier: Development Status :: 5 - Production/Stable
Classifier: Framework :: Robot Framework :: Library
Classifier: Intended Audience :: Developers
Classifier: Intended Audience :: Science/Research
Classifier: Programming Language :: Python :: 3.10
Classifier: Programming Language :: Python :: 3.11
Classifier: Programming Language :: Python :: 3.12
Classifier: Topic :: Scientific/Engineering
Requires-Python: <3.14,>=3.10
Requires-Dist: tqdm>=4.67.1
Requires-Dist: ruckig>=0.14.0
Requires-Dist: toppra>=0.6.0
Requires-Dist: pyyaml
Requires-Dist: loguru
Requires-Dist: rich>=13.9.4
Requires-Dist: numpy>=2.0.0
Requires-Dist: tyro
Requires-Dist: setuptools>=68.0.0
Requires-Dist: hydra-core
Requires-Dist: pink-dm-fork
Requires-Dist: dexmate-urdf>=0.5.2
Requires-Dist: casadi
Requires-Dist: viser
Requires-Dist: ruff
Requires-Dist: scipy
Provides-Extra: test
Requires-Dist: pyright; extra == "test"
Requires-Dist: pre-commit; extra == "test"
Requires-Dist: warp-lang>=1.6.0; extra == "test"
Requires-Dist: robot_descriptions>=1.14.0; extra == "test"
